[{"date": "2024-09-18", "c": 35.2, "o": 35.7, "h": 36.05, "l": 35.1, "v": 320203}, {"date": "2024-09-19", "c": 35.85, "o": 35.35, "h": 35.9, "l": 35.2, "v": 283732}, {"date": "2024-09-20", "c": 33.75, "o": 34.3, "h": 34.5, "l": 32.7, "v": 2169935}, {"date": "2024-09-23", "c": 33.15, "o": 33.55, "h": 33.55, "l": 32.6, "v": 1371971}, {"date": "2024-09-24", "c": 32.85, "o": 33.15, "h": 33.75, "l": 32.85, "v": 449666}, {"date": "2024-09-25", "c": 33.15, "o": 33.2, "h": 33.85, "l": 33.15, "v": 381713}, {"date": "2024-09-26", "c": 33.5, "o": 33.25, "h": 33.85, "l": 33.25, "v": 300712}, {"date": "2024-09-27", "c": 34.6, "o": 33.9, "h": 34.6, "l": 33.55, "v": 645896}, {"date": "2024-09-30", "c": 34.2, "o": 34.15, "h": 34.55, "l": 34.0, "v": 151465}, {"date": "2024-10-01", "c": 33.5, "o": 34.2, "h": 34.2, "l": 33.5, "v": 187124}, {"date": "2024-10-04", "c": 32.9, "o": 33.85, "h": 33.85, "l": 32.85, "v": 226257}, {"date": "2024-10-07", "c": 36.15, "o": 34.0, "h": 36.15, "l": 33.5, "v": 1608777}, {"date": "2024-10-08", "c": 34.05, "o": 36.15, "h": 36.2, "l": 34.05, "v": 1001470}, {"date": "2024-10-09", "c": 33.7, "o": 34.4, "h": 34.4, "l": 33.55, "v": 360728}, {"date": "2024-10-11", "c": 33.8, "o": 33.45, "h": 34.3, "l": 33.4, "v": 242660}, {"date": "2024-10-14", "c": 33.75, "o": 33.8, "h": 34.05, "l": 33.55, "v": 221159}, {"date": "2024-10-15", "c": 34.05, "o": 33.95, "h": 34.35, "l": 33.65, "v": 284963}, {"date": "2024-10-16", "c": 36.1, "o": 33.9, "h": 36.1, "l": 33.2, "v": 2646061}, {"date": "2024-10-17", "c": 36.0, "o": 35.35, "h": 36.0, "l": 33.7, "v": 926730}, {"date": "2024-10-18", "c": 34.15, "o": 35.95, "h": 35.95, "l": 34.1, "v": 815827}, {"date": "2024-10-21", "c": 33.6, "o": 34.55, "h": 34.55, "l": 33.5, "v": 667649}, {"date": "2024-10-22", "c": 33.0, "o": 33.35, "h": 33.45, "l": 32.9, "v": 535413}, {"date": "2024-10-23", "c": 32.75, "o": 33.2, "h": 33.25, "l": 32.7, "v": 342872}, {"date": "2024-10-24", "c": 32.2, "o": 32.7, "h": 32.7, "l": 32.1, "v": 536800}, {"date": "2024-10-25", "c": 32.4, "o": 32.45, "h": 32.45, "l": 32.05, "v": 268565}, {"date": "2024-10-28", "c": 32.35, "o": 32.4, "h": 32.6, "l": 32.15, "v": 189520}, {"date": "2024-10-29", "c": 31.9, "o": 32.3, "h": 32.3, "l": 31.4, "v": 431846}, {"date": "2024-10-30", "c": 32.2, "o": 31.95, "h": 32.25, "l": 31.9, "v": 181369}, {"date": "2024-11-01", "c": 32.65, "o": 31.95, "h": 32.8, "l": 31.9, "v": 244375}, {"date": "2024-11-04", "c": 31.9, "o": 32.3, "h": 32.4, "l": 31.8, "v": 357699}, {"date": "2024-11-05", "c": 31.85, "o": 31.65, "h": 32.3, "l": 31.65, "v": 223102}, {"date": "2024-11-06", "c": 32.0, "o": 32.0, "h": 32.2, "l": 31.75, "v": 110223}, {"date": "2024-11-07", "c": 32.2, "o": 32.0, "h": 32.2, "l": 31.9, "v": 83790}, {"date": "2024-11-08", "c": 32.3, "o": 32.3, "h": 33.45, "l": 32.3, "v": 331404}, {"date": "2024-11-11", "c": 34.05, "o": 34.25, "h": 35.3, "l": 33.8, "v": 1309219}, {"date": "2024-11-12", "c": 34.0, "o": 34.0, "h": 34.25, "l": 33.5, "v": 489484}, {"date": "2024-11-13", "c": 34.15, "o": 33.75, "h": 34.8, "l": 33.65, "v": 841489}, {"date": "2024-11-14", "c": 35.3, "o": 34.2, "h": 35.95, "l": 34.0, "v": 1417812}, {"date": "2024-11-15", "c": 36.0, "o": 35.65, "h": 36.95, "l": 35.45, "v": 1505702}, {"date": "2024-11-18", "c": 36.75, "o": 36.3, "h": 37.2, "l": 35.4, "v": 1243521}, {"date": "2024-11-19", "c": 37.2, "o": 36.75, "h": 37.65, "l": 36.55, "v": 888959}, {"date": "2024-11-20", "c": 37.5, "o": 37.4, "h": 38.45, "l": 37.15, "v": 1104737}, {"date": "2024-11-21", "c": 38.9, "o": 37.7, "h": 39.4, "l": 37.2, "v": 1596812}, {"date": "2024-11-22", "c": 38.5, "o": 39.2, "h": 39.7, "l": 38.4, "v": 1037499}, {"date": "2024-11-25", "c": 39.45, "o": 38.55, "h": 39.45, "l": 38.55, "v": 578035}, {"date": "2024-11-26", "c": 39.35, "o": 39.4, "h": 39.5, "l": 38.8, "v": 321659}, {"date": "2024-11-27", "c": 38.45, "o": 39.5, "h": 39.5, "l": 37.95, "v": 815314}, {"date": "2024-11-28", "c": 37.8, "o": 38.9, "h": 38.9, "l": 36.15, "v": 702198}, {"date": "2024-11-29", "c": 37.85, "o": 38.2, "h": 38.2, "l": 37.45, "v": 262055}, {"date": "2024-12-02", "c": 38.65, "o": 38.35, "h": 38.75, "l": 38.2, "v": 260658}, {"date": "2024-12-03", "c": 38.25, "o": 38.55, "h": 38.85, "l": 38.15, "v": 387022}, {"date": "2024-12-04", "c": 37.55, "o": 38.25, "h": 38.4, "l": 37.4, "v": 412404}, {"date": "2024-12-05", "c": 37.05, "o": 37.55, "h": 37.65, "l": 36.95, "v": 332286}, {"date": "2024-12-06", "c": 40.6, "o": 37.6, "h": 40.75, "l": 37.35, "v": 1776370}, {"date": "2024-12-09", "c": 39.1, "o": 40.6, "h": 41.2, "l": 39.1, "v": 1775274}, {"date": "2024-12-10", "c": 37.65, "o": 38.75, "h": 39.55, "l": 37.6, "v": 1058591}, {"date": "2024-12-11", "c": 37.9, "o": 37.6, "h": 38.35, "l": 37.2, "v": 458558}, {"date": "2024-12-12", "c": 37.55, "o": 37.8, "h": 38.25, "l": 37.55, "v": 351995}, {"date": "2024-12-13", "c": 36.75, "o": 37.65, "h": 37.65, "l": 36.6, "v": 559429}, {"date": "2024-12-16", "c": 37.6, "o": 36.65, "h": 38.7, "l": 36.65, "v": 449977}, {"date": "2024-12-17", "c": 36.6, "o": 37.35, "h": 37.4, "l": 36.6, "v": 319282}, {"date": "2024-12-18", "c": 36.8, "o": 36.5, "h": 36.8, "l": 35.85, "v": 243175}, {"date": "2024-12-19", "c": 35.7, "o": 36.1, "h": 36.55, "l": 35.5, "v": 613305}, {"date": "2024-12-20", "c": 35.1, "o": 35.95, "h": 36.75, "l": 35.0, "v": 519857}, {"date": "2024-12-23", "c": 37.35, "o": 35.55, "h": 37.4, "l": 35.5, "v": 474184}, {"date": "2024-12-24", "c": 37.4, "o": 37.6, "h": 38.05, "l": 37.15, "v": 413094}, {"date": "2024-12-25", "c": 38.1, "o": 37.5, "h": 38.25, "l": 37.3, "v": 263863}, {"date": "2024-12-26", "c": 37.8, "o": 37.85, "h": 38.45, "l": 37.8, "v": 196284}, {"date": "2024-12-27", "c": 37.6, "o": 37.65, "h": 37.85, "l": 37.35, "v": 112056}, {"date": "2024-12-30", "c": 38.75, "o": 37.8, "h": 39.75, "l": 37.8, "v": 492540}, {"date": "2024-12-31", "c": 37.9, "o": 38.65, "h": 38.65, "l": 37.7, "v": 327081}, {"date": "2025-01-02", "c": 37.9, "o": 37.9, "h": 38.7, "l": 37.6, "v": 224522}, {"date": "2025-01-03", "c": 37.5, "o": 38.0, "h": 38.25, "l": 37.5, "v": 143580}, {"date": "2025-01-06", "c": 37.9, "o": 37.5, "h": 38.25, "l": 37.5, "v": 230150}, {"date": "2025-01-07", "c": 37.8, "o": 37.95, "h": 37.95, "l": 37.45, "v": 198863}, {"date": "2025-01-08", "c": 38.4, "o": 37.55, "h": 38.45, "l": 37.4, "v": 375997}, {"date": "2025-01-09", "c": 37.6, "o": 38.35, "h": 38.6, "l": 37.3, "v": 311184}, {"date": "2025-01-10", "c": 35.4, "o": 37.05, "h": 37.4, "l": 34.4, "v": 1089719}, {"date": "2025-01-13", "c": 34.15, "o": 35.4, "h": 35.4, "l": 33.8, "v": 585081}, {"date": "2025-01-14", "c": 34.05, "o": 34.0, "h": 34.35, "l": 33.95, "v": 142284}, {"date": "2025-01-15", "c": 34.2, "o": 34.05, "h": 34.55, "l": 34.0, "v": 100687}, {"date": "2025-01-16", "c": 34.35, "o": 34.45, "h": 34.75, "l": 34.35, "v": 110230}, {"date": "2025-01-17", "c": 34.75, "o": 34.85, "h": 34.9, "l": 34.4, "v": 94252}, {"date": "2025-01-20", "c": 34.95, "o": 34.7, "h": 35.25, "l": 34.7, "v": 123011}, {"date": "2025-01-21", "c": 34.95, "o": 35.25, "h": 35.25, "l": 34.7, "v": 64860}, {"date": "2025-01-22", "c": 35.5, "o": 35.0, "h": 35.5, "l": 34.9, "v": 164027}, {"date": "2025-02-03", "c": 35.55, "o": 34.8, "h": 36.0, "l": 34.75, "v": 255527}, {"date": "2025-02-04", "c": 34.85, "o": 35.4, "h": 35.55, "l": 34.75, "v": 161434}, {"date": "2025-02-05", "c": 35.55, "o": 35.3, "h": 35.7, "l": 35.25, "v": 94004}, {"date": "2025-02-06", "c": 35.6, "o": 35.9, "h": 36.05, "l": 35.6, "v": 82903}, {"date": "2025-02-07", "c": 35.6, "o": 35.3, "h": 35.6, "l": 35.0, "v": 79466}, {"date": "2025-02-10", "c": 35.35, "o": 35.25, "h": 35.8, "l": 35.0, "v": 167165}, {"date": "2025-02-11", "c": 34.9, "o": 35.4, "h": 35.6, "l": 34.55, "v": 143096}, {"date": "2025-02-12", "c": 34.2, "o": 35.2, "h": 35.2, "l": 34.2, "v": 336261}, {"date": "2025-02-13", "c": 35.3, "o": 34.5, "h": 35.5, "l": 34.5, "v": 274916}, {"date": "2025-02-14", "c": 34.9, "o": 35.2, "h": 35.45, "l": 34.9, "v": 123638}, {"date": "2025-02-17", "c": 36.0, "o": 35.2, "h": 36.2, "l": 35.1, "v": 269670}, {"date": "2025-02-18", "c": 36.2, "o": 36.25, "h": 36.45, "l": 35.9, "v": 160526}, {"date": "2025-02-19", "c": 36.4, "o": 36.2, "h": 36.65, "l": 36.1, "v": 184605}, {"date": "2025-02-20", "c": 36.65, "o": 36.4, "h": 36.8, "l": 36.2, "v": 145482}, {"date": "2025-02-21", "c": 37.4, "o": 36.7, "h": 37.5, "l": 36.7, "v": 225206}, {"date": "2025-02-24", "c": 37.4, "o": 37.05, "h": 37.45, "l": 36.9, "v": 238638}, {"date": "2025-02-25", "c": 37.6, "o": 37.4, "h": 37.7, "l": 37.0, "v": 147797}, {"date": "2025-02-26", "c": 37.2, "o": 37.5, "h": 37.5, "l": 37.0, "v": 198581}, {"date": "2025-02-27", "c": 36.8, "o": 37.4, "h": 37.4, "l": 36.75, "v": 169996}, {"date": "2025-03-03", "c": 36.65, "o": 36.55, "h": 36.85, "l": 36.25, "v": 111682}, {"date": "2025-03-04", "c": 36.95, "o": 36.2, "h": 36.95, "l": 35.65, "v": 211163}, {"date": "2025-03-05", "c": 37.15, "o": 36.85, "h": 37.2, "l": 36.55, "v": 122644}, {"date": "2025-03-06", "c": 37.2, "o": 37.2, "h": 37.4, "l": 36.95, "v": 186618}, {"date": "2025-03-07", "c": 36.9, "o": 37.15, "h": 37.2, "l": 36.65, "v": 185503}, {"date": "2025-03-10", "c": 34.95, "o": 36.15, "h": 36.15, "l": 34.3, "v": 734767}, {"date": "2025-03-11", "c": 33.6, "o": 34.2, "h": 34.25, "l": 33.3, "v": 729570}, {"date": "2025-03-12", "c": 33.8, "o": 33.95, "h": 34.0, "l": 33.5, "v": 323347}, {"date": "2025-03-13", "c": 33.2, "o": 33.85, "h": 34.15, "l": 33.15, "v": 357985}, {"date": "2025-03-14", "c": 34.5, "o": 33.25, "h": 34.5, "l": 33.25, "v": 282830}, {"date": "2025-03-17", "c": 34.45, "o": 34.75, "h": 34.75, "l": 34.25, "v": 229440}, {"date": "2025-03-18", "c": 34.7, "o": 34.65, "h": 34.95, "l": 34.6, "v": 303058}, {"date": "2025-03-19", "c": 34.8, "o": 34.7, "h": 35.0, "l": 34.6, "v": 278960}, {"date": "2025-03-20", "c": 35.5, "o": 35.0, "h": 35.7, "l": 34.65, "v": 224346}, {"date": "2025-03-21", "c": 35.95, "o": 35.5, "h": 36.1, "l": 35.3, "v": 402260}, {"date": "2025-03-24", "c": 35.8, "o": 35.9, "h": 36.0, "l": 35.55, "v": 135081}, {"date": "2025-03-25", "c": 35.55, "o": 36.1, "h": 36.15, "l": 35.55, "v": 136683}, {"date": "2025-03-26", "c": 35.8, "o": 35.95, "h": 35.95, "l": 35.55, "v": 65747}, {"date": "2025-03-27", "c": 35.3, "o": 35.8, "h": 35.8, "l": 35.25, "v": 150052}, {"date": "2025-03-28", "c": 34.0, "o": 35.1, "h": 35.15, "l": 33.9, "v": 442949}, {"date": "2025-03-31", "c": 32.8, "o": 33.15, "h": 33.15, "l": 32.25, "v": 441894}, {"date": "2025-04-01", "c": 33.35, "o": 32.95, "h": 33.5, "l": 32.7, "v": 319779}, {"date": "2025-04-02", "c": 33.6, "o": 33.55, "h": 33.6, "l": 32.85, "v": 156331}, {"date": "2025-04-07", "c": 30.25, "o": 30.25, "h": 30.25, "l": 30.25, "v": 29537}, {"date": "2025-04-08", "c": 27.65, "o": 27.3, "h": 28.4, "l": 27.25, "v": 1857509}, {"date": "2025-04-09", "c": 24.9, "o": 28.1, "h": 28.3, "l": 24.9, "v": 1344104}, {"date": "2025-04-10", "c": 27.35, "o": 27.3, "h": 27.35, "l": 26.8, "v": 351297}, {"date": "2025-04-11", "c": 27.25, "o": 26.25, "h": 27.25, "l": 26.2, "v": 536280}, {"date": "2025-04-14", "c": 27.75, "o": 27.3, "h": 28.4, "l": 27.3, "v": 316812}, {"date": "2025-04-15", "c": 29.05, "o": 28.2, "h": 29.1, "l": 28.0, "v": 269321}, {"date": "2025-04-16", "c": 28.6, "o": 29.1, "h": 29.1, "l": 28.3, "v": 278427}, {"date": "2025-04-17", "c": 29.1, "o": 28.35, "h": 29.1, "l": 28.1, "v": 174629}, {"date": "2025-04-18", "c": 29.3, "o": 28.8, "h": 29.3, "l": 28.7, "v": 196819}, {"date": "2025-04-21", "c": 28.4, "o": 29.1, "h": 29.2, "l": 28.35, "v": 189661}, {"date": "2025-04-22", "c": 27.75, "o": 28.2, "h": 28.25, "l": 27.45, "v": 292740}, {"date": "2025-04-23", "c": 28.15, "o": 28.05, "h": 28.45, "l": 28.0, "v": 185822}, {"date": "2025-04-24", "c": 28.15, "o": 28.3, "h": 28.6, "l": 28.1, "v": 73390}, {"date": "2025-04-25", "c": 28.1, "o": 28.55, "h": 28.65, "l": 27.95, "v": 516745}, {"date": "2025-04-28", "c": 28.8, "o": 28.2, "h": 28.85, "l": 28.2, "v": 223695}, {"date": "2025-04-29", "c": 28.9, "o": 28.8, "h": 28.95, "l": 28.6, "v": 114359}, {"date": "2025-04-30", "c": 29.1, "o": 28.75, "h": 29.1, "l": 28.7, "v": 199224}, {"date": "2025-05-02", "c": 29.8, "o": 29.3, "h": 29.85, "l": 29.0, "v": 281604}, {"date": "2025-05-05", "c": 30.2, "o": 30.5, "h": 31.6, "l": 29.85, "v": 367398}, {"date": "2025-05-06", "c": 30.0, "o": 30.6, "h": 30.6, "l": 29.95, "v": 157603}, {"date": "2025-05-07", "c": 29.8, "o": 29.8, "h": 30.05, "l": 29.8, "v": 127567}, {"date": "2025-05-08", "c": 30.2, "o": 30.0, "h": 30.35, "l": 30.0, "v": 52923}, {"date": "2025-05-09", "c": 30.5, "o": 30.15, "h": 30.7, "l": 30.05, "v": 134555}, {"date": "2025-05-12", "c": 30.15, "o": 30.1, "h": 30.4, "l": 30.0, "v": 136076}, {"date": "2025-05-13", "c": 30.45, "o": 30.15, "h": 30.7, "l": 30.15, "v": 94701}, {"date": "2025-05-14", "c": 30.9, "o": 30.65, "h": 31.15, "l": 30.45, "v": 207601}, {"date": "2025-05-15", "c": 30.7, "o": 30.6, "h": 31.1, "l": 30.6, "v": 100642}, {"date": "2025-05-16", "c": 30.0, "o": 30.95, "h": 30.95, "l": 29.8, "v": 484338}, {"date": "2025-05-19", "c": 29.9, "o": 30.0, "h": 30.1, "l": 29.8, "v": 202597}, {"date": "2025-05-20", "c": 30.15, "o": 30.0, "h": 30.25, "l": 30.0, "v": 162768}, {"date": "2025-05-21", "c": 30.1, "o": 30.15, "h": 30.35, "l": 29.9, "v": 105215}, {"date": "2025-05-22", "c": 29.95, "o": 29.9, "h": 30.15, "l": 29.9, "v": 45082}, {"date": "2025-05-23", "c": 29.85, "o": 29.9, "h": 29.95, "l": 29.85, "v": 69124}, {"date": "2025-05-26", "c": 30.15, "o": 29.9, "h": 30.3, "l": 29.8, "v": 164131}, {"date": "2025-05-27", "c": 30.0, "o": 30.1, "h": 30.35, "l": 29.95, "v": 122698}, {"date": "2025-05-28", "c": 29.95, "o": 30.2, "h": 30.2, "l": 29.9, "v": 97943}, {"date": "2025-05-29", "c": 29.95, "o": 30.05, "h": 30.05, "l": 29.65, "v": 133631}, {"date": "2025-06-02", "c": 29.0, "o": 29.3, "h": 29.45, "l": 28.95, "v": 172003}, {"date": "2025-06-03", "c": 28.7, "o": 29.35, "h": 29.35, "l": 28.7, "v": 101073}, {"date": "2025-06-04", "c": 29.05, "o": 28.8, "h": 29.35, "l": 28.8, "v": 118306}, {"date": "2025-06-05", "c": 28.9, "o": 29.0, "h": 29.1, "l": 28.7, "v": 97318}, {"date": "2025-06-06", "c": 28.9, "o": 28.7, "h": 29.15, "l": 28.7, "v": 124257}, {"date": "2025-06-09", "c": 28.8, "o": 29.1, "h": 29.15, "l": 28.7, "v": 63419}, {"date": "2025-06-10", "c": 28.8, "o": 29.15, "h": 29.35, "l": 28.8, "v": 153622}, {"date": "2025-06-11", "c": 28.5, "o": 28.85, "h": 28.85, "l": 28.35, "v": 156625}, {"date": "2025-06-12", "c": 28.4, "o": 28.5, "h": 28.65, "l": 28.35, "v": 71590}, {"date": "2025-06-13", "c": 28.45, "o": 28.15, "h": 28.5, "l": 27.85, "v": 159118}, {"date": "2025-06-16", "c": 28.05, "o": 28.15, "h": 28.2, "l": 27.95, "v": 71800}, {"date": "2025-06-17", "c": 27.9, "o": 28.05, "h": 28.2, "l": 27.8, "v": 143069}, {"date": "2025-06-18", "c": 27.8, "o": 27.9, "h": 28.05, "l": 27.7, "v": 96818}, {"date": "2025-06-19", "c": 27.4, "o": 27.75, "h": 27.8, "l": 27.35, "v": 247735}, {"date": "2025-06-20", "c": 27.05, "o": 27.35, "h": 27.4, "l": 26.9, "v": 306561}, {"date": "2025-06-23", "c": 26.75, "o": 27.0, "h": 27.0, "l": 26.25, "v": 164910}, {"date": "2025-06-24", "c": 27.4, "o": 26.8, "h": 27.45, "l": 26.65, "v": 166677}, {"date": "2025-06-25", "c": 27.2, "o": 27.15, "h": 27.2, "l": 26.9, "v": 99555}, {"date": "2025-06-26", "c": 27.65, "o": 27.35, "h": 27.8, "l": 27.1, "v": 117263}, {"date": "2025-06-27", "c": 27.8, "o": 27.45, "h": 27.85, "l": 27.45, "v": 141238}, {"date": "2025-06-30", "c": 27.25, "o": 27.5, "h": 27.65, "l": 27.2, "v": 104195}, {"date": "2025-07-01", "c": 28.3, "o": 27.3, "h": 28.5, "l": 27.25, "v": 221346}, {"date": "2025-07-02", "c": 29.4, "o": 28.45, "h": 29.9, "l": 28.0, "v": 322307}, {"date": "2025-07-03", "c": 29.3, "o": 29.3, "h": 29.4, "l": 29.0, "v": 143386}, {"date": "2025-07-04", "c": 28.65, "o": 29.6, "h": 29.6, "l": 28.55, "v": 122922}, {"date": "2025-07-07", "c": 28.2, "o": 28.9, "h": 28.9, "l": 28.2, "v": 104776}, {"date": "2025-07-08", "c": 27.9, "o": 28.15, "h": 28.2, "l": 27.9, "v": 47157}, {"date": "2025-07-09", "c": 27.7, "o": 28.2, "h": 28.3, "l": 27.7, "v": 52901}, {"date": "2025-07-10", "c": 27.55, "o": 27.65, "h": 28.05, "l": 27.55, "v": 100974}, {"date": "2025-07-11", "c": 27.5, "o": 27.5, "h": 27.6, "l": 27.4, "v": 125773}, {"date": "2025-07-14", "c": 28.0, "o": 27.5, "h": 28.4, "l": 27.35, "v": 166168}, {"date": "2025-07-15", "c": 27.85, "o": 27.7, "h": 28.5, "l": 27.7, "v": 190758}, {"date": "2025-07-16", "c": 27.8, "o": 27.8, "h": 28.15, "l": 27.8, "v": 114516}, {"date": "2025-07-17", "c": 28.25, "o": 28.0, "h": 28.3, "l": 28.0, "v": 147160}, {"date": "2025-07-18", "c": 28.2, "o": 28.25, "h": 28.6, "l": 28.05, "v": 205154}, {"date": "2025-07-21", "c": 28.0, "o": 28.2, "h": 28.25, "l": 27.9, "v": 96423}, {"date": "2025-07-22", "c": 27.45, "o": 27.85, "h": 27.9, "l": 27.25, "v": 182670}, {"date": "2025-07-23", "c": 27.8, "o": 27.45, "h": 27.85, "l": 27.45, "v": 52615}, {"date": "2025-07-24", "c": 27.6, "o": 27.7, "h": 27.8, "l": 27.6, "v": 149682}, {"date": "2025-07-25", "c": 27.6, "o": 27.7, "h": 27.8, "l": 27.6, "v": 183460}, {"date": "2025-07-28", "c": 27.6, "o": 27.85, "h": 27.85, "l": 27.45, "v": 214780}, {"date": "2025-07-29", "c": 27.35, "o": 27.55, "h": 27.55, "l": 27.25, "v": 498456}, {"date": "2025-07-30", "c": 27.3, "o": 27.35, "h": 27.45, "l": 27.2, "v": 51714}, {"date": "2025-07-31", "c": 26.9, "o": 27.3, "h": 27.3, "l": 26.8, "v": 215292}, {"date": "2025-08-01", "c": 26.8, "o": 26.8, "h": 26.95, "l": 26.3, "v": 312988}, {"date": "2025-08-04", "c": 26.75, "o": 26.7, "h": 26.95, "l": 26.5, "v": 139813}, {"date": "2025-08-05", "c": 26.85, "o": 26.8, "h": 27.1, "l": 26.8, "v": 188080}, {"date": "2025-08-06", "c": 26.95, "o": 26.85, "h": 27.2, "l": 26.65, "v": 118756}, {"date": "2025-08-07", "c": 26.9, "o": 27.15, "h": 27.15, "l": 26.85, "v": 39416}, {"date": "2025-08-08", "c": 26.9, "o": 26.8, "h": 27.05, "l": 26.8, "v": 147528}, {"date": "2025-08-11", "c": 26.9, "o": 26.9, "h": 27.05, "l": 26.75, "v": 107791}, {"date": "2025-08-12", "c": 27.0, "o": 26.8, "h": 27.1, "l": 26.8, "v": 131527}, {"date": "2025-08-13", "c": 27.2, "o": 27.15, "h": 27.35, "l": 27.0, "v": 137018}, {"date": "2025-08-14", "c": 27.5, "o": 27.35, "h": 27.6, "l": 27.2, "v": 120377}, {"date": "2025-08-15", "c": 27.7, "o": 27.5, "h": 27.7, "l": 27.3, "v": 136229}, {"date": "2025-08-18", "c": 28.3, "o": 27.7, "h": 28.35, "l": 27.7, "v": 215059}, {"date": "2025-08-19", "c": 28.15, "o": 28.35, "h": 28.35, "l": 27.85, "v": 639001}, {"date": "2025-08-20", "c": 27.5, "o": 28.25, "h": 28.25, "l": 27.2, "v": 751845}, {"date": "2025-08-21", "c": 27.7, "o": 27.55, "h": 28.0, "l": 27.55, "v": 321300}, {"date": "2025-08-22", "c": 27.6, "o": 28.15, "h": 28.35, "l": 27.6, "v": 519505}, {"date": "2025-08-25", "c": 25.35, "o": 25.6, "h": 25.6, "l": 25.2, "v": 604557}, {"date": "2025-08-26", "c": 24.9, "o": 25.15, "h": 25.25, "l": 24.9, "v": 227171}, {"date": "2025-08-27", "c": 24.65, "o": 24.9, "h": 24.9, "l": 24.55, "v": 224562}, {"date": "2025-08-28", "c": 24.15, "o": 24.45, "h": 24.45, "l": 24.0, "v": 644526}, {"date": "2025-08-29", "c": 23.85, "o": 24.15, "h": 24.15, "l": 23.8, "v": 252356}, {"date": "2025-09-01", "c": 23.4, "o": 23.85, "h": 23.85, "l": 23.4, "v": 371889}, {"date": "2025-09-02", "c": 23.7, "o": 23.4, "h": 23.75, "l": 23.25, "v": 217258}, {"date": "2025-09-03", "c": 23.55, "o": 23.65, "h": 23.65, "l": 23.45, "v": 107452}, {"date": "2025-09-04", "c": 25.5, "o": 23.7, "h": 25.9, "l": 23.7, "v": 651077}, {"date": "2025-09-05", "c": 25.2, "o": 25.8, "h": 25.8, "l": 25.15, "v": 262989}, {"date": "2025-09-08", "c": 25.7, "o": 25.2, "h": 25.8, "l": 24.95, "v": 256046}, {"date": "2025-09-09", "c": 26.0, "o": 25.65, "h": 26.25, "l": 25.65, "v": 382565}, {"date": "2025-09-10", "c": 25.55, "o": 25.9, "h": 25.9, "l": 25.35, "v": 203659}, {"date": "2025-09-11", "c": 25.15, "o": 25.0, "h": 25.45, "l": 25.0, "v": 145817}, {"date": "2025-09-12", "c": 25.7, "o": 25.45, "h": 25.9, "l": 25.3, "v": 156237}, {"date": "2025-09-15", "c": 25.25, "o": 25.7, "h": 25.75, "l": 25.25, "v": 120409}, {"date": "2025-09-16", "c": 25.15, "o": 25.4, "h": 25.75, "l": 25.1, "v": 187861}, {"date": "2025-09-17", "c": 25.45, "o": 25.15, "h": 25.5, "l": 25.15, "v": 117834}, {"date": "2025-09-18", "c": 25.4, "o": 25.5, "h": 25.6, "l": 25.25, "v": 188879}, {"date": "2025-09-19", "c": 24.95, "o": 25.55, "h": 25.55, "l": 24.95, "v": 294141}, {"date": "2025-09-22", "c": 25.2, "o": 25.0, "h": 25.2, "l": 24.9, "v": 136229}, {"date": "2025-09-23", "c": 25.05, "o": 25.0, "h": 25.25, "l": 24.95, "v": 139009}, {"date": "2025-09-24", "c": 25.05, "o": 25.25, "h": 25.5, "l": 25.0, "v": 73417}, {"date": "2025-09-25", "c": 25.3, "o": 25.4, "h": 25.5, "l": 25.1, "v": 103115}, {"date": "2025-09-26", "c": 25.2, "o": 25.2, "h": 25.35, "l": 25.15, "v": 144631}, {"date": "2025-09-30", "c": 25.4, "o": 25.2, "h": 25.4, "l": 25.15, "v": 122555}, {"date": "2025-10-01", "c": 25.0, "o": 25.4, "h": 25.4, "l": 24.9, "v": 176228}, {"date": "2025-10-02", "c": 24.6, "o": 25.05, "h": 25.1, "l": 24.6, "v": 241308}, {"date": "2025-10-03", "c": 24.45, "o": 24.6, "h": 24.7, "l": 24.15, "v": 302718}, {"date": "2025-10-07", "c": 24.1, "o": 24.5, "h": 25.0, "l": 24.05, "v": 365241}, {"date": "2025-10-08", "c": 23.7, "o": 24.1, "h": 24.1, "l": 23.6, "v": 352990}, {"date": "2025-10-09", "c": 23.7, "o": 23.7, "h": 23.8, "l": 23.6, "v": 219614}, {"date": "2025-10-13", "c": 23.5, "o": 23.5, "h": 23.55, "l": 22.8, "v": 333211}, {"date": "2025-10-14", "c": 23.05, "o": 23.6, "h": 23.7, "l": 22.95, "v": 435731}, {"date": "2025-10-15", "c": 22.05, "o": 23.2, "h": 23.2, "l": 22.05, "v": 2451230}, {"date": "2025-10-16", "c": 23.7, "o": 22.5, "h": 24.0, "l": 22.5, "v": 941515}, {"date": "2025-10-17", "c": 23.75, "o": 23.7, "h": 24.3, "l": 23.3, "v": 775871}, {"date": "2025-10-20", "c": 23.8, "o": 23.8, "h": 23.9, "l": 23.45, "v": 181101}, {"date": "2025-10-21", "c": 23.8, "o": 23.95, "h": 24.05, "l": 23.8, "v": 119022}, {"date": "2025-10-22", "c": 23.85, "o": 23.75, "h": 23.9, "l": 23.75, "v": 97200}, {"date": "2025-10-23", "c": 23.7, "o": 23.65, "h": 23.95, "l": 23.6, "v": 53893}, {"date": "2025-10-27", "c": 24.6, "o": 23.85, "h": 24.9, "l": 23.75, "v": 402110}, {"date": "2025-10-28", "c": 24.25, "o": 24.7, "h": 24.7, "l": 24.15, "v": 150288}, {"date": "2025-10-29", "c": 25.0, "o": 24.25, "h": 25.3, "l": 24.25, "v": 368635}, {"date": "2025-10-30", "c": 25.2, "o": 25.15, "h": 25.25, "l": 25.0, "v": 252476}, {"date": "2025-10-31", "c": 27.25, "o": 25.4, "h": 27.5, "l": 25.4, "v": 1616286}, {"date": "2025-11-03", "c": 26.7, "o": 27.5, "h": 27.7, "l": 26.5, "v": 800533}, {"date": "2025-11-04", "c": 25.35, "o": 26.8, "h": 26.95, "l": 25.3, "v": 843357}, {"date": "2025-11-05", "c": 24.95, "o": 25.1, "h": 25.35, "l": 24.75, "v": 542229}, {"date": "2025-11-06", "c": 25.4, "o": 25.1, "h": 25.7, "l": 24.85, "v": 140513}, {"date": "2025-11-07", "c": 25.05, "o": 25.05, "h": 25.3, "l": 25.0, "v": 109991}, {"date": "2025-11-10", "c": 25.2, "o": 25.7, "h": 25.9, "l": 25.15, "v": 186826}, {"date": "2025-11-11", "c": 25.45, "o": 25.6, "h": 25.75, "l": 25.15, "v": 207445}, {"date": "2025-11-12", "c": 26.25, "o": 25.55, "h": 26.3, "l": 25.55, "v": 208944}, {"date": "2025-11-13", "c": 25.95, "o": 26.2, "h": 26.3, "l": 25.55, "v": 312512}, {"date": "2025-11-14", "c": 25.65, "o": 25.5, "h": 26.05, "l": 25.4, "v": 177141}, {"date": "2025-11-17", "c": 25.95, "o": 25.45, "h": 26.05, "l": 25.15, "v": 271963}, {"date": "2025-11-18", "c": 25.05, "o": 25.55, "h": 25.75, "l": 24.95, "v": 236554}, {"date": "2025-11-19", "c": 24.9, "o": 25.3, "h": 25.3, "l": 24.8, "v": 126405}, {"date": "2025-11-20", "c": 25.4, "o": 25.15, "h": 25.4, "l": 25.05, "v": 125703}, {"date": "2025-11-21", "c": 25.1, "o": 25.2, "h": 25.3, "l": 24.8, "v": 158985}, {"date": "2025-11-24", "c": 25.45, "o": 25.2, "h": 25.5, "l": 25.15, "v": 109414}, {"date": "2025-11-25", "c": 27.45, "o": 27.1, "h": 27.95, "l": 27.0, "v": 1526748}, {"date": "2025-11-26", "c": 27.55, "o": 27.5, "h": 28.1, "l": 27.1, "v": 1062672}, {"date": "2025-11-27", "c": 28.8, "o": 27.55, "h": 28.85, "l": 27.55, "v": 1080564}, {"date": "2025-11-28", "c": 28.0, "o": 28.65, "h": 28.65, "l": 27.8, "v": 421075}, {"date": "2025-12-01", "c": 27.95, "o": 28.0, "h": 28.3, "l": 27.55, "v": 273090}, {"date": "2025-12-02", "c": 28.95, "o": 28.25, "h": 28.95, "l": 27.95, "v": 293410}, {"date": "2025-12-03", "c": 29.1, "o": 29.0, "h": 29.2, "l": 28.6, "v": 246880}, {"date": "2025-12-04", "c": 29.35, "o": 29.2, "h": 29.5, "l": 28.9, "v": 193940}, {"date": "2025-12-05", "c": 29.15, "o": 29.1, "h": 29.3, "l": 28.7, "v": 185495}, {"date": "2025-12-08", "c": 28.85, "o": 29.3, "h": 29.35, "l": 28.8, "v": 228456}, {"date": "2025-12-09", "c": 29.4, "o": 28.85, "h": 29.45, "l": 28.8, "v": 517735}, {"date": "2025-12-10", "c": 29.65, "o": 29.3, "h": 30.05, "l": 29.2, "v": 285856}, {"date": "2025-12-11", "c": 28.95, "o": 29.75, "h": 29.75, "l": 28.8, "v": 287047}, {"date": "2025-12-12", "c": 28.9, "o": 29.05, "h": 29.3, "l": 28.85, "v": 105041}, {"date": "2025-12-15", "c": 28.25, "o": 29.0, "h": 29.0, "l": 28.25, "v": 306120}, {"date": "2025-12-16", "c": 28.45, "o": 28.15, "h": 28.5, "l": 27.95, "v": 264159}, {"date": "2025-12-17", "c": 28.1, "o": 28.45, "h": 28.75, "l": 28.1, "v": 156084}, {"date": "2025-12-18", "c": 28.35, "o": 28.0, "h": 28.4, "l": 27.95, "v": 151300}, {"date": "2025-12-19", "c": 28.4, "o": 28.25, "h": 28.7, "l": 28.15, "v": 147914}, {"date": "2025-12-22", "c": 28.7, "o": 28.3, "h": 28.9, "l": 28.2, "v": 284333}, {"date": "2025-12-23", "c": 28.3, "o": 28.7, "h": 28.9, "l": 28.25, "v": 136808}, {"date": "2025-12-24", "c": 29.0, "o": 28.35, "h": 29.35, "l": 28.25, "v": 456766}, {"date": "2025-12-26", "c": 29.1, "o": 29.15, "h": 29.8, "l": 29.05, "v": 216000}, {"date": "2025-12-29", "c": 29.0, "o": 29.1, "h": 29.25, "l": 28.7, "v": 240419}, {"date": "2025-12-30", "c": 29.1, "o": 28.95, "h": 29.25, "l": 28.65, "v": 169615}, {"date": "2025-12-31", "c": 29.05, "o": 29.1, "h": 29.25, "l": 28.95, "v": 113905}, {"date": "2026-01-02", "c": 29.25, "o": 29.1, "h": 29.25, "l": 29.0, "v": 169233}, {"date": "2026-01-05", "c": 28.45, "o": 29.25, "h": 29.25, "l": 28.4, "v": 356045}, {"date": "2026-01-06", "c": 29.15, "o": 28.5, "h": 29.25, "l": 28.5, "v": 556967}, {"date": "2026-01-07", "c": 29.1, "o": 28.95, "h": 29.3, "l": 28.95, "v": 160298}, {"date": "2026-01-08", "c": 29.1, "o": 29.2, "h": 29.25, "l": 28.85, "v": 128519}, {"date": "2026-01-09", "c": 29.3, "o": 29.0, "h": 29.4, "l": 28.85, "v": 257598}, {"date": "2026-01-12", "c": 32.2, "o": 32.15, "h": 32.2, "l": 31.85, "v": 1920920}, {"date": "2026-01-13", "c": 31.95, "o": 32.7, "h": 33.8, "l": 31.6, "v": 2084083}, {"date": "2026-01-14", "c": 30.7, "o": 31.9, "h": 32.0, "l": 30.4, "v": 965139}, {"date": "2026-01-15", "c": 30.2, "o": 30.8, "h": 30.8, "l": 29.95, "v": 595341}, {"date": "2026-01-16", "c": 30.9, "o": 30.35, "h": 30.9, "l": 30.15, "v": 555904}, {"date": "2026-01-19", "c": 30.25, "o": 30.8, "h": 30.8, "l": 30.0, "v": 673928}, {"date": "2026-01-20", "c": 29.6, "o": 30.15, "h": 30.15, "l": 29.6, "v": 343874}, {"date": "2026-01-21", "c": 29.05, "o": 29.55, "h": 29.6, "l": 29.0, "v": 430512}, {"date": "2026-01-22", "c": 29.55, "o": 29.15, "h": 29.6, "l": 29.05, "v": 293336}, {"date": "2026-01-23", "c": 30.05, "o": 29.35, "h": 30.2, "l": 28.9, "v": 357606}, {"date": "2026-01-26", "c": 29.9, "o": 30.2, "h": 30.2, "l": 29.75, "v": 278904}, {"date": "2026-01-27", "c": 29.5, "o": 30.3, "h": 30.4, "l": 29.3, "v": 337753}, {"date": "2026-01-28", "c": 29.8, "o": 29.5, "h": 30.0, "l": 29.5, "v": 322070}, {"date": "2026-01-29", "c": 29.35, "o": 29.8, "h": 29.8, "l": 29.25, "v": 242183}, {"date": "2026-01-30", "c": 28.9, "o": 29.15, "h": 29.2, "l": 28.75, "v": 246462}, {"date": "2026-02-02", "c": 28.0, "o": 28.85, "h": 28.85, "l": 28.0, "v": 284056}, {"date": "2026-02-03", "c": 28.55, "o": 28.2, "h": 28.75, "l": 28.05, "v": 267549}, {"date": "2026-02-04", "c": 28.75, "o": 28.55, "h": 29.0, "l": 28.4, "v": 179819}, {"date": "2026-02-05", "c": 28.45, "o": 28.35, "h": 28.85, "l": 28.25, "v": 214082}, {"date": "2026-02-06", "c": 27.85, "o": 28.3, "h": 28.6, "l": 27.55, "v": 496082}, {"date": "2026-02-09", "c": 29.15, "o": 28.15, "h": 29.75, "l": 28.0, "v": 709842}, {"date": "2026-02-10", "c": 30.15, "o": 29.05, "h": 30.3, "l": 28.9, "v": 692038}, {"date": "2026-02-11", "c": 29.5, "o": 29.85, "h": 29.85, "l": 29.2, "v": 514316}, {"date": "2026-02-23", "c": 29.9, "o": 30.1, "h": 30.5, "l": 29.7, "v": 558772}, {"date": "2026-02-24", "c": 30.85, "o": 29.9, "h": 31.1, "l": 29.8, "v": 703055}, {"date": "2026-02-25", "c": 31.1, "o": 31.0, "h": 31.75, "l": 30.85, "v": 543397}, {"date": "2026-02-26", "c": 32.35, "o": 31.15, "h": 32.5, "l": 31.15, "v": 1006418}, {"date": "2026-03-02", "c": 32.1, "o": 32.0, "h": 32.4, "l": 31.3, "v": 598075}, {"date": "2026-03-03", "c": 31.45, "o": 31.8, "h": 31.9, "l": 31.15, "v": 427667}, {"date": "2026-03-04", "c": 29.8, "o": 30.8, "h": 30.9, "l": 29.5, "v": 602927}, {"date": "2026-03-05", "c": 30.7, "o": 30.25, "h": 30.8, "l": 30.25, "v": 259620}, {"date": "2026-03-06", "c": 30.5, "o": 30.55, "h": 30.7, "l": 30.15, "v": 101386}, {"date": "2026-03-09", "c": 29.15, "o": 29.5, "h": 29.5, "l": 28.65, "v": 418724}, {"date": "2026-03-10", "c": 29.8, "o": 29.5, "h": 30.55, "l": 29.5, "v": 260740}, {"date": "2026-03-11", "c": 29.85, "o": 29.75, "h": 30.05, "l": 29.75, "v": 173841}, {"date": "2026-03-12", "c": 29.1, "o": 29.4, "h": 29.5, "l": 29.1, "v": 253775}, {"date": "2026-03-13", "c": 29.0, "o": 28.95, "h": 29.5, "l": 28.8, "v": 239886}, {"date": "2026-03-16", "c": 29.5, "o": 29.05, "h": 29.9, "l": 28.6, "v": 390092}, {"date": "2026-03-17", "c": 30.35, "o": 29.65, "h": 30.65, "l": 29.55, "v": 348626}, {"date": "2026-03-18", "c": 30.65, "o": 30.75, "h": 31.0, "l": 30.3, "v": 235532}, {"date": "2026-03-19", "c": 29.8, "o": 30.2, "h": 30.5, "l": 29.8, "v": 279570}, {"date": "2026-03-20", "c": 29.8, "o": 29.95, "h": 30.4, "l": 29.8, "v": 225593}, {"date": "2026-03-23", "c": 29.05, "o": 29.3, "h": 29.5, "l": 29.0, "v": 244419}, {"date": "2026-03-24", "c": 28.8, "o": 29.2, "h": 29.25, "l": 28.55, "v": 277177}, {"date": "2026-03-25", "c": 29.45, "o": 29.15, "h": 29.6, "l": 29.1, "v": 263143}, {"date": "2026-03-26", "c": 29.5, "o": 29.7, "h": 29.7, "l": 29.3, "v": 142305}, {"date": "2026-03-27", "c": 29.45, "o": 29.3, "h": 29.5, "l": 29.05, "v": 110107}, {"date": "2026-03-30", "c": 29.4, "o": 29.1, "h": 29.5, "l": 29.05, "v": 158975}, {"date": "2026-03-31", "c": 28.95, "o": 29.2, "h": 29.25, "l": 28.55, "v": 389717}, {"date": "2026-04-01", "c": 30.2, "o": 29.3, "h": 30.3, "l": 29.25, "v": 347240}, {"date": "2026-04-02", "c": 29.6, "o": 30.3, "h": 30.4, "l": 29.55, "v": 154630}, {"date": "2026-04-07", "c": 30.45, "o": 29.75, "h": 30.65, "l": 29.75, "v": 318196}, {"date": "2026-04-08", "c": 30.95, "o": 30.45, "h": 31.25, "l": 30.45, "v": 266726}, {"date": "2026-04-09", "c": 31.0, "o": 31.0, "h": 31.15, "l": 30.75, "v": 226087}, {"date": "2026-04-10", "c": 33.0, "o": 32.6, "h": 33.9, "l": 32.1, "v": 1633056}, {"date": "2026-04-13", "c": 36.3, "o": 36.0, "h": 36.3, "l": 35.0, "v": 3080214}, {"date": "2026-04-14", "c": 37.7, "o": 36.3, "h": 37.85, "l": 36.3, "v": 2540354}, {"date": "2026-04-15", "c": 39.2, "o": 38.05, "h": 40.0, "l": 38.05, "v": 1868590}, {"date": "2026-04-16", "c": 39.7, "o": 39.85, "h": 40.25, "l": 39.35, "v": 1202816}, {"date": "2026-04-17", "c": 36.7, "o": 39.25, "h": 39.3, "l": 36.3, "v": 2241513}, {"date": "2026-04-20", "c": 36.2, "o": 36.75, "h": 37.85, "l": 36.2, "v": 661966}, {"date": "2026-04-21", "c": 36.25, "o": 36.5, "h": 37.05, "l": 35.85, "v": 478772}, {"date": "2026-04-22", "c": 34.85, "o": 36.25, "h": 36.25, "l": 34.7, "v": 857282}, {"date": "2026-04-23", "c": 34.15, "o": 34.8, "h": 35.75, "l": 33.75, "v": 869095}, {"date": "2026-04-24", "c": 33.9, "o": 34.35, "h": 34.7, "l": 33.4, "v": 575635}, {"date": "2026-04-27", "c": 34.95, "o": 34.55, "h": 35.4, "l": 33.25, "v": 842496}, {"date": "2026-04-28", "c": 34.4, "o": 35.0, "h": 35.0, "l": 34.3, "v": 330184}, {"date": "2026-04-29", "c": 34.55, "o": 34.4, "h": 34.85, "l": 34.4, "v": 263177}, {"date": "2026-04-30", "c": 34.05, "o": 34.6, "h": 34.6, "l": 33.6, "v": 481402}, {"date": "2026-05-04", "c": 34.85, "o": 34.2, "h": 35.55, "l": 34.2, "v": 591127}, {"date": "2026-05-05", "c": 33.9, "o": 34.85, "h": 34.85, "l": 33.9, "v": 555457}, {"date": "2026-05-06", "c": 33.9, "o": 34.5, "h": 34.5, "l": 33.8, "v": 342629}, {"date": "2026-05-07", "c": 34.6, "o": 33.8, "h": 34.8, "l": 33.45, "v": 526189}, {"date": "2026-05-08", "c": 34.65, "o": 34.9, "h": 35.2, "l": 33.85, "v": 304090}, {"date": "2026-05-11", "c": 34.35, "o": 35.8, "h": 36.3, "l": 33.35, "v": 1141176}, {"date": "2026-05-12", "c": 33.7, "o": 33.55, "h": 34.35, "l": 33.3, "v": 757097}, {"date": "2026-05-13", "c": 34.1, "o": 33.9, "h": 34.1, "l": 33.45, "v": 403776}, {"date": "2026-05-14", "c": 33.35, "o": 34.1, "h": 34.35, "l": 33.35, "v": 455690}, {"date": "2026-05-15", "c": 33.3, "o": 33.55, "h": 34.05, "l": 33.3, "v": 406434}, {"date": "2026-05-18", "c": 33.65, "o": 33.3, "h": 33.7, "l": 32.7, "v": 324658}]