[{"date": "2024-08-27", "c": 14.35, "o": 14.3, "h": 14.35, "l": 14.2, "v": 773198}, {"date": "2024-08-28", "c": 14.65, "o": 14.5, "h": 14.7, "l": 14.5, "v": 1209439}, {"date": "2024-08-29", "c": 14.4, "o": 14.65, "h": 14.65, "l": 14.4, "v": 821700}, {"date": "2024-08-30", "c": 14.5, "o": 14.5, "h": 14.65, "l": 14.45, "v": 860299}, {"date": "2024-09-02", "c": 14.5, "o": 14.65, "h": 14.65, "l": 14.45, "v": 465894}, {"date": "2024-09-03", "c": 14.35, "o": 14.6, "h": 14.6, "l": 14.3, "v": 514582}, {"date": "2024-09-04", "c": 13.95, "o": 14.0, "h": 14.05, "l": 13.5, "v": 1615736}, {"date": "2024-09-05", "c": 13.9, "o": 14.0, "h": 14.1, "l": 13.9, "v": 523311}, {"date": "2024-09-06", "c": 13.9, "o": 14.05, "h": 14.05, "l": 13.9, "v": 679315}, {"date": "2024-09-09", "c": 13.95, "o": 14.05, "h": 14.05, "l": 13.8, "v": 589072}, {"date": "2024-09-10", "c": 14.5, "o": 14.1, "h": 14.5, "l": 14.05, "v": 1646972}, {"date": "2024-09-11", "c": 14.2, "o": 14.5, "h": 14.5, "l": 14.15, "v": 786903}, {"date": "2024-09-12", "c": 14.15, "o": 14.3, "h": 14.3, "l": 14.15, "v": 419133}, {"date": "2024-09-13", "c": 14.2, "o": 14.15, "h": 14.3, "l": 14.15, "v": 309312}, {"date": "2024-09-16", "c": 14.4, "o": 14.25, "h": 14.4, "l": 14.2, "v": 893060}, {"date": "2024-09-18", "c": 14.55, "o": 14.4, "h": 14.7, "l": 14.35, "v": 1396585}, {"date": "2024-09-19", "c": 14.55, "o": 14.6, "h": 14.6, "l": 14.5, "v": 540326}, {"date": "2024-09-20", "c": 14.65, "o": 14.65, "h": 14.75, "l": 14.6, "v": 1041563}, {"date": "2024-09-23", "c": 14.4, "o": 14.65, "h": 14.7, "l": 14.4, "v": 878899}, {"date": "2024-09-24", "c": 14.45, "o": 14.4, "h": 14.5, "l": 14.4, "v": 323341}, {"date": "2024-09-25", "c": 14.75, "o": 14.5, "h": 14.8, "l": 14.5, "v": 1363384}, {"date": "2024-09-26", "c": 14.5, "o": 14.7, "h": 14.8, "l": 14.45, "v": 850143}, {"date": "2024-09-27", "c": 14.55, "o": 14.55, "h": 14.6, "l": 14.5, "v": 339211}, {"date": "2024-09-30", "c": 14.95, "o": 14.75, "h": 15.0, "l": 14.65, "v": 3453473}, {"date": "2024-10-01", "c": 15.1, "o": 14.95, "h": 15.1, "l": 14.8, "v": 2052415}, {"date": "2024-10-04", "c": 14.8, "o": 15.15, "h": 15.15, "l": 14.8, "v": 1092853}, {"date": "2024-10-07", "c": 14.85, "o": 14.9, "h": 14.95, "l": 14.65, "v": 791427}, {"date": "2024-10-08", "c": 14.65, "o": 14.85, "h": 14.85, "l": 14.6, "v": 536384}, {"date": "2024-10-09", "c": 14.4, "o": 14.75, "h": 14.75, "l": 14.4, "v": 929167}, {"date": "2024-10-11", "c": 14.3, "o": 14.4, "h": 14.45, "l": 14.3, "v": 580858}, {"date": "2024-10-14", "c": 14.25, "o": 14.3, "h": 14.35, "l": 14.2, "v": 933116}, {"date": "2024-10-15", "c": 14.25, "o": 14.3, "h": 14.5, "l": 14.25, "v": 645529}, {"date": "2024-10-16", "c": 14.25, "o": 14.3, "h": 14.3, "l": 14.15, "v": 348313}, {"date": "2024-10-17", "c": 14.35, "o": 14.25, "h": 14.35, "l": 14.2, "v": 493079}, {"date": "2024-10-18", "c": 14.2, "o": 14.35, "h": 14.35, "l": 14.15, "v": 558402}, {"date": "2024-10-21", "c": 14.15, "o": 14.2, "h": 14.25, "l": 14.1, "v": 860130}, {"date": "2024-10-22", "c": 14.15, "o": 14.15, "h": 14.25, "l": 14.1, "v": 492481}, {"date": "2024-10-23", "c": 14.15, "o": 14.2, "h": 14.3, "l": 14.15, "v": 315122}, {"date": "2024-10-24", "c": 14.15, "o": 14.25, "h": 14.3, "l": 14.15, "v": 437173}, {"date": "2024-10-25", "c": 14.1, "o": 14.25, "h": 14.25, "l": 14.05, "v": 813024}, {"date": "2024-10-28", "c": 14.1, "o": 14.1, "h": 14.2, "l": 14.1, "v": 458215}, {"date": "2024-10-29", "c": 13.95, "o": 14.1, "h": 14.15, "l": 13.85, "v": 1108889}, {"date": "2024-10-30", "c": 13.85, "o": 13.95, "h": 14.0, "l": 13.85, "v": 462690}, {"date": "2024-11-01", "c": 14.1, "o": 13.8, "h": 14.1, "l": 13.7, "v": 852603}, {"date": "2024-11-04", "c": 13.95, "o": 14.1, "h": 14.1, "l": 13.9, "v": 366116}, {"date": "2024-11-05", "c": 14.0, "o": 14.0, "h": 14.1, "l": 13.9, "v": 234345}, {"date": "2024-11-06", "c": 13.85, "o": 14.05, "h": 14.05, "l": 13.85, "v": 395742}, {"date": "2024-11-07", "c": 13.85, "o": 13.95, "h": 13.95, "l": 13.8, "v": 716759}, {"date": "2024-11-08", "c": 13.7, "o": 13.8, "h": 13.85, "l": 13.6, "v": 1022275}, {"date": "2024-11-11", "c": 13.5, "o": 13.65, "h": 13.65, "l": 13.5, "v": 1056499}, {"date": "2024-11-12", "c": 13.25, "o": 13.55, "h": 13.6, "l": 13.25, "v": 1683002}, {"date": "2024-11-13", "c": 13.1, "o": 13.25, "h": 13.35, "l": 13.1, "v": 1283318}, {"date": "2024-11-14", "c": 12.2, "o": 13.0, "h": 13.0, "l": 12.1, "v": 4234933}, {"date": "2024-11-15", "c": 12.0, "o": 12.2, "h": 12.25, "l": 11.9, "v": 3694800}, {"date": "2024-11-18", "c": 12.2, "o": 12.0, "h": 12.4, "l": 12.0, "v": 1246795}, {"date": "2024-11-19", "c": 12.55, "o": 12.2, "h": 12.7, "l": 12.15, "v": 1039387}, {"date": "2024-11-20", "c": 12.45, "o": 12.5, "h": 12.55, "l": 12.35, "v": 772348}, {"date": "2024-11-21", "c": 12.6, "o": 12.45, "h": 12.6, "l": 12.35, "v": 587837}, {"date": "2024-11-22", "c": 12.55, "o": 12.6, "h": 12.7, "l": 12.5, "v": 489211}, {"date": "2024-11-25", "c": 12.25, "o": 12.6, "h": 12.85, "l": 12.25, "v": 12287707}, {"date": "2024-11-26", "c": 12.3, "o": 12.25, "h": 12.35, "l": 12.05, "v": 1543577}, {"date": "2024-11-27", "c": 12.1, "o": 12.25, "h": 12.35, "l": 12.05, "v": 666780}, {"date": "2024-11-28", "c": 12.05, "o": 12.1, "h": 12.25, "l": 12.0, "v": 902489}, {"date": "2024-11-29", "c": 12.5, "o": 12.05, "h": 12.6, "l": 12.05, "v": 1023764}, {"date": "2024-12-02", "c": 12.15, "o": 12.5, "h": 12.55, "l": 12.15, "v": 760280}, {"date": "2024-12-03", "c": 12.15, "o": 12.25, "h": 12.4, "l": 12.15, "v": 460912}, {"date": "2024-12-04", "c": 12.25, "o": 12.25, "h": 12.35, "l": 12.15, "v": 484197}, {"date": "2024-12-05", "c": 12.05, "o": 12.2, "h": 12.25, "l": 12.05, "v": 758778}, {"date": "2024-12-06", "c": 12.0, "o": 12.05, "h": 12.2, "l": 11.95, "v": 980414}, {"date": "2024-12-09", "c": 11.85, "o": 11.9, "h": 12.0, "l": 11.85, "v": 1073835}, {"date": "2024-12-10", "c": 11.85, "o": 11.85, "h": 12.05, "l": 11.85, "v": 507024}, {"date": "2024-12-11", "c": 11.85, "o": 11.9, "h": 11.95, "l": 11.8, "v": 544123}, {"date": "2024-12-12", "c": 11.8, "o": 11.85, "h": 12.0, "l": 11.7, "v": 588331}, {"date": "2024-12-13", "c": 11.45, "o": 11.8, "h": 11.8, "l": 11.3, "v": 1283318}, {"date": "2024-12-16", "c": 11.2, "o": 11.45, "h": 11.55, "l": 11.15, "v": 993828}, {"date": "2024-12-17", "c": 11.25, "o": 11.25, "h": 11.3, "l": 11.2, "v": 504143}, {"date": "2024-12-18", "c": 11.25, "o": 11.3, "h": 11.35, "l": 11.2, "v": 366989}, {"date": "2024-12-19", "c": 10.9, "o": 11.15, "h": 11.15, "l": 10.8, "v": 1278068}, {"date": "2024-12-20", "c": 10.9, "o": 10.95, "h": 11.15, "l": 10.9, "v": 782590}, {"date": "2024-12-23", "c": 10.85, "o": 11.0, "h": 11.15, "l": 10.85, "v": 708757}, {"date": "2024-12-24", "c": 10.95, "o": 10.95, "h": 11.1, "l": 10.85, "v": 641232}, {"date": "2024-12-25", "c": 11.0, "o": 11.0, "h": 11.0, "l": 10.9, "v": 393499}, {"date": "2024-12-26", "c": 12.0, "o": 11.0, "h": 12.1, "l": 11.0, "v": 3965915}, {"date": "2024-12-27", "c": 11.5, "o": 11.85, "h": 11.9, "l": 11.5, "v": 2098554}, {"date": "2024-12-30", "c": 11.3, "o": 11.5, "h": 11.7, "l": 11.3, "v": 978910}, {"date": "2024-12-31", "c": 11.45, "o": 11.35, "h": 11.6, "l": 11.25, "v": 994520}, {"date": "2025-01-02", "c": 11.3, "o": 11.45, "h": 11.5, "l": 11.25, "v": 640800}, {"date": "2025-01-03", "c": 11.3, "o": 11.3, "h": 11.65, "l": 11.25, "v": 1045075}, {"date": "2025-01-06", "c": 11.3, "o": 11.4, "h": 11.5, "l": 11.3, "v": 632133}, {"date": "2025-01-07", "c": 11.05, "o": 11.5, "h": 11.5, "l": 11.0, "v": 1001878}, {"date": "2025-01-08", "c": 11.05, "o": 11.05, "h": 11.35, "l": 10.8, "v": 1735375}, {"date": "2025-01-09", "c": 11.25, "o": 11.05, "h": 11.65, "l": 11.0, "v": 1916520}, {"date": "2025-01-10", "c": 11.35, "o": 11.45, "h": 11.6, "l": 11.05, "v": 2048965}, {"date": "2025-01-13", "c": 10.7, "o": 11.15, "h": 11.2, "l": 10.7, "v": 2332819}, {"date": "2025-01-14", "c": 10.7, "o": 10.7, "h": 10.8, "l": 10.6, "v": 803743}, {"date": "2025-01-15", "c": 10.7, "o": 10.75, "h": 10.85, "l": 10.65, "v": 542209}, {"date": "2025-01-16", "c": 10.7, "o": 10.8, "h": 10.9, "l": 10.65, "v": 639006}, {"date": "2025-01-17", "c": 10.7, "o": 10.8, "h": 10.8, "l": 10.65, "v": 537770}, {"date": "2025-01-20", "c": 10.8, "o": 10.7, "h": 10.85, "l": 10.6, "v": 716924}, {"date": "2025-01-21", "c": 10.85, "o": 10.8, "h": 10.95, "l": 10.8, "v": 672385}, {"date": "2025-01-22", "c": 10.8, "o": 10.9, "h": 10.9, "l": 10.8, "v": 449748}, {"date": "2025-02-03", "c": 11.2, "o": 10.75, "h": 11.3, "l": 10.6, "v": 1946506}, {"date": "2025-02-04", "c": 10.9, "o": 11.2, "h": 11.3, "l": 10.9, "v": 890414}, {"date": "2025-02-05", "c": 11.4, "o": 11.05, "h": 11.55, "l": 11.0, "v": 1625572}, {"date": "2025-02-06", "c": 11.8, "o": 11.5, "h": 12.15, "l": 11.5, "v": 3118677}, {"date": "2025-02-07", "c": 11.7, "o": 11.8, "h": 11.8, "l": 11.65, "v": 837730}, {"date": "2025-02-10", "c": 11.6, "o": 11.7, "h": 11.75, "l": 11.5, "v": 884385}, {"date": "2025-02-11", "c": 11.7, "o": 12.05, "h": 12.05, "l": 11.55, "v": 1431421}, {"date": "2025-02-12", "c": 11.7, "o": 11.8, "h": 12.05, "l": 11.65, "v": 1509773}, {"date": "2025-02-13", "c": 11.75, "o": 11.85, "h": 11.85, "l": 11.75, "v": 683608}, {"date": "2025-02-14", "c": 12.15, "o": 11.75, "h": 12.15, "l": 11.75, "v": 1831776}, {"date": "2025-02-17", "c": 11.85, "o": 12.2, "h": 12.25, "l": 11.85, "v": 1360366}, {"date": "2025-02-18", "c": 11.8, "o": 11.9, "h": 12.0, "l": 11.75, "v": 518030}, {"date": "2025-02-19", "c": 11.65, "o": 11.8, "h": 11.8, "l": 11.6, "v": 717817}, {"date": "2025-02-20", "c": 11.65, "o": 11.65, "h": 11.7, "l": 11.55, "v": 436364}, {"date": "2025-02-21", "c": 11.55, "o": 11.65, "h": 11.75, "l": 11.55, "v": 705455}, {"date": "2025-02-24", "c": 12.0, "o": 11.6, "h": 12.05, "l": 11.6, "v": 1979912}, {"date": "2025-02-25", "c": 11.7, "o": 12.1, "h": 12.1, "l": 11.7, "v": 1527008}, {"date": "2025-02-26", "c": 11.55, "o": 11.7, "h": 11.75, "l": 11.55, "v": 775682}, {"date": "2025-02-27", "c": 11.5, "o": 11.65, "h": 11.65, "l": 11.5, "v": 495311}, {"date": "2025-03-03", "c": 11.2, "o": 11.65, "h": 11.65, "l": 11.2, "v": 865183}, {"date": "2025-03-04", "c": 11.25, "o": 11.2, "h": 11.3, "l": 11.1, "v": 616550}, {"date": "2025-03-05", "c": 11.2, "o": 11.3, "h": 11.35, "l": 11.15, "v": 416387}, {"date": "2025-03-06", "c": 11.1, "o": 11.3, "h": 11.35, "l": 11.1, "v": 828225}, {"date": "2025-03-07", "c": 11.15, "o": 11.15, "h": 11.2, "l": 11.05, "v": 490126}, {"date": "2025-03-10", "c": 11.15, "o": 11.3, "h": 11.3, "l": 11.05, "v": 538948}, {"date": "2025-03-11", "c": 11.0, "o": 11.05, "h": 11.05, "l": 10.8, "v": 957276}, {"date": "2025-03-12", "c": 11.1, "o": 11.0, "h": 11.15, "l": 10.95, "v": 479755}, {"date": "2025-03-13", "c": 10.85, "o": 11.2, "h": 11.2, "l": 10.8, "v": 818790}, {"date": "2025-03-14", "c": 11.05, "o": 10.8, "h": 11.1, "l": 10.8, "v": 617657}, {"date": "2025-03-17", "c": 11.05, "o": 11.1, "h": 11.2, "l": 11.05, "v": 661249}, {"date": "2025-03-18", "c": 11.15, "o": 11.1, "h": 11.25, "l": 11.05, "v": 489160}, {"date": "2025-03-19", "c": 11.1, "o": 11.2, "h": 11.3, "l": 11.1, "v": 411267}, {"date": "2025-03-20", "c": 11.15, "o": 11.15, "h": 11.25, "l": 11.1, "v": 497987}, {"date": "2025-03-21", "c": 11.4, "o": 11.25, "h": 11.5, "l": 11.25, "v": 1077655}, {"date": "2025-03-24", "c": 11.35, "o": 11.45, "h": 11.65, "l": 11.35, "v": 947409}, {"date": "2025-03-25", "c": 11.3, "o": 11.5, "h": 11.5, "l": 11.25, "v": 404465}, {"date": "2025-03-26", "c": 11.4, "o": 11.3, "h": 11.6, "l": 11.3, "v": 663312}, {"date": "2025-03-27", "c": 11.3, "o": 11.35, "h": 11.4, "l": 11.2, "v": 766060}, {"date": "2025-03-28", "c": 11.0, "o": 11.3, "h": 11.4, "l": 11.0, "v": 780725}, {"date": "2025-03-31", "c": 10.6, "o": 10.8, "h": 10.95, "l": 10.6, "v": 1024052}, {"date": "2025-04-01", "c": 10.75, "o": 10.65, "h": 10.85, "l": 10.65, "v": 584514}, {"date": "2025-04-02", "c": 10.75, "o": 10.75, "h": 10.8, "l": 10.65, "v": 397505}, {"date": "2025-04-07", "c": 9.68, "o": 9.68, "h": 9.68, "l": 9.68, "v": 525519}, {"date": "2025-04-08", "c": 8.97, "o": 8.73, "h": 9.1, "l": 8.72, "v": 3002254}, {"date": "2025-04-09", "c": 8.08, "o": 8.99, "h": 8.99, "l": 8.08, "v": 3111796}, {"date": "2025-04-10", "c": 8.88, "o": 8.87, "h": 8.88, "l": 8.71, "v": 876878}, {"date": "2025-04-11", "c": 9.15, "o": 8.97, "h": 9.19, "l": 8.47, "v": 1236835}, {"date": "2025-04-14", "c": 9.3, "o": 9.23, "h": 9.39, "l": 9.18, "v": 748395}, {"date": "2025-04-15", "c": 9.51, "o": 9.3, "h": 9.52, "l": 9.28, "v": 519814}, {"date": "2025-04-16", "c": 9.43, "o": 9.51, "h": 9.56, "l": 9.38, "v": 480162}, {"date": "2025-04-17", "c": 9.64, "o": 9.37, "h": 9.68, "l": 9.29, "v": 414686}, {"date": "2025-04-18", "c": 9.58, "o": 9.53, "h": 9.74, "l": 9.53, "v": 559605}, {"date": "2025-04-21", "c": 9.31, "o": 9.6, "h": 9.6, "l": 9.26, "v": 524872}, {"date": "2025-04-22", "c": 9.22, "o": 9.3, "h": 9.35, "l": 9.15, "v": 366706}, {"date": "2025-04-23", "c": 9.45, "o": 9.34, "h": 9.54, "l": 9.34, "v": 487163}, {"date": "2025-04-24", "c": 9.41, "o": 9.42, "h": 9.54, "l": 9.41, "v": 188485}, {"date": "2025-04-25", "c": 9.52, "o": 9.43, "h": 9.54, "l": 9.43, "v": 292399}, {"date": "2025-04-28", "c": 9.6, "o": 9.54, "h": 9.69, "l": 9.54, "v": 515915}, {"date": "2025-04-29", "c": 9.85, "o": 9.6, "h": 9.89, "l": 9.6, "v": 418060}, {"date": "2025-04-30", "c": 10.0, "o": 9.99, "h": 10.1, "l": 9.93, "v": 970054}, {"date": "2025-05-02", "c": 10.15, "o": 10.1, "h": 10.15, "l": 10.0, "v": 631752}, {"date": "2025-05-05", "c": 9.89, "o": 10.15, "h": 10.2, "l": 9.87, "v": 733641}, {"date": "2025-05-06", "c": 9.85, "o": 9.98, "h": 9.98, "l": 9.82, "v": 267955}, {"date": "2025-05-07", "c": 9.97, "o": 9.85, "h": 9.98, "l": 9.85, "v": 278961}, {"date": "2025-05-08", "c": 10.0, "o": 10.0, "h": 10.1, "l": 9.97, "v": 347045}, {"date": "2025-05-09", "c": 10.0, "o": 10.0, "h": 10.1, "l": 9.94, "v": 414242}, {"date": "2025-05-12", "c": 10.0, "o": 10.0, "h": 10.1, "l": 9.96, "v": 339642}, {"date": "2025-05-13", "c": 9.94, "o": 10.1, "h": 10.1, "l": 9.93, "v": 468410}, {"date": "2025-05-14", "c": 9.91, "o": 9.95, "h": 9.98, "l": 9.9, "v": 290417}, {"date": "2025-05-15", "c": 9.81, "o": 9.98, "h": 9.98, "l": 9.8, "v": 367754}, {"date": "2025-05-16", "c": 9.8, "o": 9.82, "h": 9.89, "l": 9.78, "v": 321426}, {"date": "2025-05-19", "c": 10.05, "o": 9.81, "h": 10.55, "l": 9.81, "v": 1145750}, {"date": "2025-05-20", "c": 10.1, "o": 10.15, "h": 10.15, "l": 10.0, "v": 341793}, {"date": "2025-05-21", "c": 10.05, "o": 10.1, "h": 10.1, "l": 9.98, "v": 307664}, {"date": "2025-05-22", "c": 10.1, "o": 10.05, "h": 10.15, "l": 9.96, "v": 349441}, {"date": "2025-05-23", "c": 10.0, "o": 10.1, "h": 10.3, "l": 10.0, "v": 644778}, {"date": "2025-05-26", "c": 9.97, "o": 10.0, "h": 10.05, "l": 9.95, "v": 354306}, {"date": "2025-05-27", "c": 9.9, "o": 10.0, "h": 10.1, "l": 9.9, "v": 449648}, {"date": "2025-05-28", "c": 9.89, "o": 9.99, "h": 9.99, "l": 9.86, "v": 231783}, {"date": "2025-05-29", "c": 9.72, "o": 9.8, "h": 9.86, "l": 9.71, "v": 862150}, {"date": "2025-06-02", "c": 9.35, "o": 9.59, "h": 9.64, "l": 9.32, "v": 999816}, {"date": "2025-06-03", "c": 9.32, "o": 9.35, "h": 9.38, "l": 9.2, "v": 666027}, {"date": "2025-06-04", "c": 9.36, "o": 9.47, "h": 9.47, "l": 9.31, "v": 291417}, {"date": "2025-06-05", "c": 9.31, "o": 9.36, "h": 9.43, "l": 9.31, "v": 292543}, {"date": "2025-06-06", "c": 9.36, "o": 9.32, "h": 9.39, "l": 9.28, "v": 465150}, {"date": "2025-06-09", "c": 9.35, "o": 9.36, "h": 9.36, "l": 9.24, "v": 338397}, {"date": "2025-06-10", "c": 9.36, "o": 9.32, "h": 9.41, "l": 9.32, "v": 316995}, {"date": "2025-06-11", "c": 9.4, "o": 9.4, "h": 9.44, "l": 9.36, "v": 313216}, {"date": "2025-06-12", "c": 9.54, "o": 9.36, "h": 9.58, "l": 9.32, "v": 777315}, {"date": "2025-06-13", "c": 9.42, "o": 9.59, "h": 9.64, "l": 9.41, "v": 790948}, {"date": "2025-06-16", "c": 9.3, "o": 9.36, "h": 9.36, "l": 9.26, "v": 411757}, {"date": "2025-06-17", "c": 9.21, "o": 9.3, "h": 9.36, "l": 9.21, "v": 424523}, {"date": "2025-06-18", "c": 9.33, "o": 9.21, "h": 9.35, "l": 9.2, "v": 495527}, {"date": "2025-06-19", "c": 9.13, "o": 9.32, "h": 9.32, "l": 9.1, "v": 542233}, {"date": "2025-06-20", "c": 9.6, "o": 9.2, "h": 10.0, "l": 9.0, "v": 3405054}, {"date": "2025-06-23", "c": 9.44, "o": 9.75, "h": 9.9, "l": 9.38, "v": 2086277}, {"date": "2025-06-24", "c": 9.51, "o": 9.48, "h": 9.63, "l": 9.46, "v": 782595}, {"date": "2025-06-25", "c": 9.51, "o": 9.52, "h": 9.55, "l": 9.45, "v": 400570}, {"date": "2025-06-26", "c": 9.41, "o": 9.48, "h": 9.55, "l": 9.36, "v": 559976}, {"date": "2025-06-27", "c": 9.45, "o": 9.41, "h": 9.47, "l": 9.39, "v": 387066}, {"date": "2025-06-30", "c": 9.22, "o": 9.53, "h": 9.53, "l": 9.22, "v": 613885}, {"date": "2025-07-01", "c": 9.06, "o": 9.29, "h": 9.29, "l": 9.01, "v": 1381366}, {"date": "2025-07-02", "c": 8.98, "o": 8.99, "h": 9.04, "l": 8.8, "v": 1541815}, {"date": "2025-07-03", "c": 8.97, "o": 9.03, "h": 9.07, "l": 8.97, "v": 475316}, {"date": "2025-07-04", "c": 8.56, "o": 8.97, "h": 8.97, "l": 8.53, "v": 1885931}, {"date": "2025-07-07", "c": 8.5, "o": 8.56, "h": 8.56, "l": 8.21, "v": 751959}, {"date": "2025-07-08", "c": 8.28, "o": 8.5, "h": 8.5, "l": 8.23, "v": 1106082}, {"date": "2025-07-09", "c": 8.23, "o": 8.29, "h": 8.33, "l": 8.21, "v": 575747}, {"date": "2025-07-10", "c": 8.2, "o": 8.16, "h": 8.25, "l": 8.12, "v": 1107156}, {"date": "2025-07-11", "c": 8.34, "o": 8.19, "h": 8.51, "l": 8.18, "v": 794604}, {"date": "2025-07-14", "c": 8.23, "o": 8.35, "h": 8.39, "l": 8.23, "v": 436243}, {"date": "2025-07-15", "c": 8.28, "o": 8.25, "h": 8.32, "l": 8.21, "v": 467317}, {"date": "2025-07-16", "c": 8.29, "o": 8.28, "h": 8.33, "l": 8.27, "v": 324003}, {"date": "2025-07-17", "c": 8.72, "o": 8.33, "h": 8.88, "l": 8.33, "v": 1629544}, {"date": "2025-07-18", "c": 8.52, "o": 8.72, "h": 8.72, "l": 8.52, "v": 568776}, {"date": "2025-07-21", "c": 8.58, "o": 8.46, "h": 8.65, "l": 8.46, "v": 443941}, {"date": "2025-07-22", "c": 8.35, "o": 8.61, "h": 8.62, "l": 8.33, "v": 586254}, {"date": "2025-07-23", "c": 7.52, "o": 7.52, "h": 7.52, "l": 7.52, "v": 3677694}, {"date": "2025-07-24", "c": 7.75, "o": 7.45, "h": 7.95, "l": 7.44, "v": 2431530}, {"date": "2025-07-25", "c": 8.14, "o": 7.7, "h": 8.16, "l": 7.68, "v": 1060948}, {"date": "2025-07-28", "c": 7.99, "o": 8.15, "h": 8.15, "l": 7.9, "v": 825946}, {"date": "2025-07-29", "c": 7.8, "o": 7.9, "h": 7.95, "l": 7.8, "v": 810940}, {"date": "2025-07-30", "c": 7.62, "o": 7.77, "h": 7.83, "l": 7.61, "v": 705256}, {"date": "2025-07-31", "c": 7.91, "o": 7.62, "h": 7.97, "l": 7.55, "v": 487847}, {"date": "2025-08-01", "c": 7.9, "o": 7.69, "h": 7.91, "l": 7.69, "v": 257130}, {"date": "2025-08-04", "c": 8.03, "o": 7.9, "h": 8.15, "l": 7.8, "v": 792532}, {"date": "2025-08-05", "c": 8.29, "o": 8.03, "h": 8.31, "l": 8.03, "v": 449157}, {"date": "2025-08-06", "c": 8.28, "o": 8.42, "h": 8.42, "l": 8.13, "v": 346620}, {"date": "2025-08-07", "c": 8.18, "o": 8.28, "h": 8.29, "l": 8.16, "v": 412354}, {"date": "2025-08-08", "c": 8.23, "o": 8.12, "h": 8.3, "l": 8.11, "v": 319815}, {"date": "2025-08-11", "c": 8.61, "o": 8.31, "h": 8.62, "l": 8.23, "v": 578903}, {"date": "2025-08-12", "c": 9.23, "o": 8.61, "h": 9.47, "l": 8.61, "v": 2991168}, {"date": "2025-08-13", "c": 9.06, "o": 9.23, "h": 9.45, "l": 9.06, "v": 1791503}, {"date": "2025-08-14", "c": 9.07, "o": 9.08, "h": 9.12, "l": 8.88, "v": 969421}, {"date": "2025-08-15", "c": 9.12, "o": 9.1, "h": 9.3, "l": 9.08, "v": 854789}, {"date": "2025-08-18", "c": 9.22, "o": 9.14, "h": 9.32, "l": 9.14, "v": 787633}, {"date": "2025-08-19", "c": 9.16, "o": 9.22, "h": 9.28, "l": 8.99, "v": 1083600}, {"date": "2025-08-20", "c": 9.67, "o": 9.88, "h": 9.99, "l": 9.38, "v": 3622281}, {"date": "2025-08-21", "c": 9.86, "o": 9.72, "h": 9.93, "l": 9.72, "v": 2153402}, {"date": "2025-08-22", "c": 10.05, "o": 9.82, "h": 10.15, "l": 9.82, "v": 2318744}, {"date": "2025-08-25", "c": 9.93, "o": 10.25, "h": 10.35, "l": 9.92, "v": 2360595}, {"date": "2025-08-26", "c": 9.78, "o": 9.99, "h": 9.99, "l": 9.69, "v": 1616108}, {"date": "2025-08-27", "c": 9.91, "o": 9.81, "h": 10.05, "l": 9.76, "v": 1300871}, {"date": "2025-08-28", "c": 9.76, "o": 9.92, "h": 9.92, "l": 9.7, "v": 1409868}, {"date": "2025-08-29", "c": 9.59, "o": 9.78, "h": 9.78, "l": 9.59, "v": 1264838}, {"date": "2025-09-01", "c": 9.5, "o": 9.59, "h": 9.72, "l": 9.5, "v": 1138759}, {"date": "2025-09-02", "c": 9.42, "o": 9.6, "h": 9.67, "l": 9.41, "v": 748808}, {"date": "2025-09-03", "c": 9.61, "o": 9.44, "h": 9.62, "l": 9.44, "v": 828959}, {"date": "2025-09-04", "c": 9.67, "o": 9.61, "h": 9.71, "l": 9.56, "v": 776801}, {"date": "2025-09-05", "c": 9.69, "o": 9.68, "h": 9.72, "l": 9.48, "v": 1149120}, {"date": "2025-09-08", "c": 9.55, "o": 9.69, "h": 9.74, "l": 9.42, "v": 1436752}, {"date": "2025-09-09", "c": 9.5, "o": 9.5, "h": 9.58, "l": 9.4, "v": 861789}, {"date": "2025-09-10", "c": 9.5, "o": 9.51, "h": 9.53, "l": 9.41, "v": 857309}, {"date": "2025-09-11", "c": 9.44, "o": 9.46, "h": 9.48, "l": 9.31, "v": 1253708}, {"date": "2025-09-12", "c": 9.39, "o": 9.44, "h": 9.5, "l": 9.35, "v": 792219}, {"date": "2025-09-15", "c": 9.24, "o": 9.39, "h": 9.45, "l": 9.08, "v": 1144692}, {"date": "2025-09-16", "c": 8.95, "o": 9.19, "h": 9.19, "l": 8.94, "v": 1366429}, {"date": "2025-09-17", "c": 8.87, "o": 8.95, "h": 9.04, "l": 8.83, "v": 825247}, {"date": "2025-09-18", "c": 8.77, "o": 8.93, "h": 8.95, "l": 8.74, "v": 804276}, {"date": "2025-09-19", "c": 8.35, "o": 8.77, "h": 8.94, "l": 8.35, "v": 12850353}, {"date": "2025-09-22", "c": 8.69, "o": 8.39, "h": 8.95, "l": 8.39, "v": 2582146}, {"date": "2025-09-23", "c": 8.57, "o": 8.76, "h": 8.76, "l": 8.56, "v": 868650}, {"date": "2025-09-24", "c": 8.52, "o": 8.57, "h": 8.68, "l": 8.47, "v": 785724}, {"date": "2025-09-25", "c": 8.86, "o": 8.52, "h": 8.96, "l": 8.52, "v": 1410773}, {"date": "2025-09-26", "c": 8.69, "o": 8.87, "h": 8.98, "l": 8.69, "v": 733512}, {"date": "2025-09-30", "c": 8.7, "o": 8.63, "h": 8.73, "l": 8.57, "v": 421747}, {"date": "2025-10-01", "c": 9.17, "o": 8.76, "h": 9.42, "l": 8.76, "v": 2054507}, {"date": "2025-10-02", "c": 9.1, "o": 9.4, "h": 9.57, "l": 9.05, "v": 2719032}, {"date": "2025-10-03", "c": 9.12, "o": 9.11, "h": 9.21, "l": 9.03, "v": 963948}, {"date": "2025-10-07", "c": 8.85, "o": 9.11, "h": 9.12, "l": 8.81, "v": 1796251}, {"date": "2025-10-08", "c": 8.67, "o": 8.78, "h": 8.85, "l": 8.67, "v": 1037109}, {"date": "2025-10-09", "c": 8.73, "o": 8.69, "h": 8.8, "l": 8.67, "v": 803046}, {"date": "2025-10-13", "c": 8.8, "o": 8.54, "h": 8.8, "l": 8.43, "v": 1026795}, {"date": "2025-10-14", "c": 8.58, "o": 8.81, "h": 8.94, "l": 8.57, "v": 738560}, {"date": "2025-10-15", "c": 8.37, "o": 8.56, "h": 8.59, "l": 8.36, "v": 1224868}, {"date": "2025-10-16", "c": 8.33, "o": 8.47, "h": 8.5, "l": 8.31, "v": 600791}, {"date": "2025-10-17", "c": 8.25, "o": 8.33, "h": 8.48, "l": 8.21, "v": 738742}, {"date": "2025-10-20", "c": 8.1, "o": 8.21, "h": 8.26, "l": 8.03, "v": 1259689}, {"date": "2025-10-21", "c": 8.12, "o": 8.1, "h": 8.18, "l": 8.05, "v": 777940}, {"date": "2025-10-22", "c": 8.17, "o": 8.12, "h": 8.22, "l": 8.08, "v": 633518}, {"date": "2025-10-23", "c": 8.38, "o": 8.22, "h": 8.5, "l": 8.13, "v": 1123390}, {"date": "2025-10-27", "c": 9.08, "o": 9.21, "h": 9.21, "l": 8.9, "v": 8836099}, {"date": "2025-10-28", "c": 9.19, "o": 9.07, "h": 9.38, "l": 9.02, "v": 2945055}, {"date": "2025-10-29", "c": 9.35, "o": 9.25, "h": 9.64, "l": 9.25, "v": 2737512}, {"date": "2025-10-30", "c": 9.15, "o": 9.4, "h": 9.48, "l": 9.14, "v": 1519269}, {"date": "2025-10-31", "c": 9.09, "o": 9.21, "h": 9.21, "l": 9.07, "v": 1200521}, {"date": "2025-11-03", "c": 9.1, "o": 9.09, "h": 9.35, "l": 9.0, "v": 1072815}, {"date": "2025-11-04", "c": 9.21, "o": 9.16, "h": 9.33, "l": 9.11, "v": 889505}, {"date": "2025-11-05", "c": 9.27, "o": 9.22, "h": 9.44, "l": 9.1, "v": 869360}, {"date": "2025-11-06", "c": 9.1, "o": 9.27, "h": 9.27, "l": 9.05, "v": 1033181}, {"date": "2025-11-07", "c": 9.14, "o": 9.09, "h": 9.18, "l": 9.03, "v": 478253}, {"date": "2025-11-10", "c": 9.03, "o": 9.14, "h": 9.18, "l": 8.93, "v": 940864}, {"date": "2025-11-11", "c": 9.14, "o": 9.0, "h": 9.28, "l": 9.0, "v": 1096387}, {"date": "2025-11-12", "c": 9.64, "o": 9.15, "h": 9.8, "l": 9.15, "v": 3036671}, {"date": "2025-11-13", "c": 9.52, "o": 9.7, "h": 9.91, "l": 9.51, "v": 2520211}, {"date": "2025-11-14", "c": 9.46, "o": 9.5, "h": 9.64, "l": 9.45, "v": 1091249}, {"date": "2025-11-17", "c": 9.33, "o": 9.57, "h": 9.63, "l": 9.33, "v": 925574}, {"date": "2025-11-18", "c": 9.07, "o": 9.31, "h": 9.31, "l": 9.04, "v": 924029}, {"date": "2025-11-19", "c": 9.07, "o": 9.11, "h": 9.16, "l": 9.0, "v": 470729}, {"date": "2025-11-20", "c": 9.23, "o": 9.13, "h": 9.26, "l": 9.05, "v": 698963}, {"date": "2025-11-21", "c": 9.16, "o": 9.2, "h": 9.41, "l": 9.0, "v": 1948921}, {"date": "2025-11-24", "c": 9.12, "o": 9.2, "h": 9.35, "l": 9.05, "v": 1126562}, {"date": "2025-11-25", "c": 9.34, "o": 9.16, "h": 9.4, "l": 9.03, "v": 1851386}, {"date": "2025-11-26", "c": 9.59, "o": 9.4, "h": 9.66, "l": 9.4, "v": 2225878}, {"date": "2025-11-27", "c": 9.94, "o": 9.64, "h": 9.96, "l": 9.61, "v": 1507611}, {"date": "2025-11-28", "c": 9.78, "o": 9.98, "h": 10.15, "l": 9.77, "v": 2180810}, {"date": "2025-12-01", "c": 9.98, "o": 9.78, "h": 9.98, "l": 9.7, "v": 863604}, {"date": "2025-12-02", "c": 10.25, "o": 10.3, "h": 10.85, "l": 10.1, "v": 2998684}, {"date": "2025-12-03", "c": 11.05, "o": 10.25, "h": 11.25, "l": 10.15, "v": 5732499}, {"date": "2025-12-04", "c": 11.0, "o": 11.15, "h": 11.3, "l": 10.9, "v": 3943290}, {"date": "2025-12-05", "c": 11.3, "o": 11.1, "h": 11.3, "l": 10.9, "v": 2500167}, {"date": "2025-12-08", "c": 11.1, "o": 11.55, "h": 11.8, "l": 11.1, "v": 4939758}, {"date": "2025-12-09", "c": 11.45, "o": 11.05, "h": 11.45, "l": 10.8, "v": 2905283}, {"date": "2025-12-10", "c": 11.25, "o": 11.5, "h": 11.55, "l": 11.2, "v": 1675804}, {"date": "2025-12-11", "c": 11.5, "o": 11.3, "h": 11.5, "l": 11.25, "v": 1896654}, {"date": "2025-12-12", "c": 12.65, "o": 12.65, "h": 12.65, "l": 12.65, "v": 9908881}, {"date": "2025-12-15", "c": 13.9, "o": 13.9, "h": 13.9, "l": 13.9, "v": 4804007}, {"date": "2025-12-16", "c": 13.7, "o": 15.2, "h": 15.2, "l": 13.15, "v": 29517024}, {"date": "2025-12-17", "c": 13.05, "o": 13.8, "h": 13.8, "l": 12.8, "v": 9378194}, {"date": "2025-12-18", "c": 12.25, "o": 12.9, "h": 13.0, "l": 12.25, "v": 4868741}, {"date": "2025-12-19", "c": 12.4, "o": 12.55, "h": 12.95, "l": 12.2, "v": 3333499}, {"date": "2025-12-22", "c": 12.1, "o": 12.4, "h": 12.45, "l": 12.0, "v": 3233423}, {"date": "2025-12-23", "c": 12.15, "o": 12.25, "h": 12.45, "l": 12.05, "v": 2093002}, {"date": "2025-12-24", "c": 12.1, "o": 12.2, "h": 12.3, "l": 12.05, "v": 1325220}, {"date": "2025-12-26", "c": 11.95, "o": 12.15, "h": 12.4, "l": 11.9, "v": 2752693}, {"date": "2025-12-29", "c": 12.85, "o": 12.0, "h": 13.1, "l": 12.0, "v": 11577933}, {"date": "2025-12-30", "c": 12.95, "o": 12.75, "h": 13.2, "l": 12.55, "v": 5275426}, {"date": "2025-12-31", "c": 13.4, "o": 13.0, "h": 13.75, "l": 13.0, "v": 7125875}, {"date": "2026-01-02", "c": 13.15, "o": 13.35, "h": 13.9, "l": 13.1, "v": 5535850}, {"date": "2026-01-05", "c": 13.3, "o": 13.1, "h": 13.4, "l": 13.0, "v": 4535534}, {"date": "2026-01-06", "c": 14.0, "o": 13.3, "h": 14.05, "l": 13.2, "v": 5509381}, {"date": "2026-01-07", "c": 14.85, "o": 15.35, "h": 15.35, "l": 14.45, "v": 14863048}, {"date": "2026-01-08", "c": 15.6, "o": 15.15, "h": 16.15, "l": 15.0, "v": 14953990}, {"date": "2026-01-09", "c": 15.35, "o": 16.0, "h": 16.4, "l": 15.0, "v": 12573534}, {"date": "2026-01-12", "c": 14.65, "o": 15.35, "h": 15.55, "l": 14.4, "v": 10074304}, {"date": "2026-01-13", "c": 14.45, "o": 15.05, "h": 15.05, "l": 14.25, "v": 6720566}, {"date": "2026-01-14", "c": 14.3, "o": 14.5, "h": 14.6, "l": 14.1, "v": 4708864}, {"date": "2026-01-15", "c": 14.65, "o": 14.5, "h": 15.0, "l": 14.35, "v": 5370150}, {"date": "2026-01-16", "c": 14.4, "o": 14.75, "h": 15.05, "l": 14.4, "v": 5427422}, {"date": "2026-01-19", "c": 14.3, "o": 14.6, "h": 14.75, "l": 14.2, "v": 4674876}, {"date": "2026-01-20", "c": 14.15, "o": 14.25, "h": 14.4, "l": 14.1, "v": 2797486}, {"date": "2026-01-21", "c": 14.05, "o": 14.3, "h": 14.4, "l": 14.05, "v": 4138631}, {"date": "2026-01-22", "c": 14.25, "o": 14.2, "h": 14.55, "l": 13.8, "v": 6075538}, {"date": "2026-01-23", "c": 14.3, "o": 14.2, "h": 14.4, "l": 14.15, "v": 2790862}, {"date": "2026-01-26", "c": 14.85, "o": 14.45, "h": 14.95, "l": 14.2, "v": 6274578}, {"date": "2026-01-27", "c": 14.85, "o": 15.65, "h": 16.15, "l": 14.85, "v": 15691123}, {"date": "2026-01-28", "c": 14.45, "o": 15.0, "h": 15.6, "l": 14.45, "v": 9665827}, {"date": "2026-01-29", "c": 13.65, "o": 14.5, "h": 14.5, "l": 13.65, "v": 7524188}, {"date": "2026-01-30", "c": 13.6, "o": 13.85, "h": 13.95, "l": 13.5, "v": 2881756}, {"date": "2026-02-02", "c": 13.25, "o": 13.65, "h": 13.75, "l": 13.15, "v": 2618795}, {"date": "2026-02-03", "c": 13.3, "o": 13.45, "h": 13.55, "l": 13.25, "v": 1546398}, {"date": "2026-02-04", "c": 13.4, "o": 13.3, "h": 13.4, "l": 13.2, "v": 1206491}, {"date": "2026-02-05", "c": 12.6, "o": 13.4, "h": 13.4, "l": 12.6, "v": 4910316}, {"date": "2026-02-06", "c": 12.35, "o": 12.6, "h": 12.7, "l": 12.1, "v": 3121575}, {"date": "2026-02-09", "c": 12.3, "o": 12.55, "h": 12.65, "l": 12.25, "v": 1745639}, {"date": "2026-02-10", "c": 12.1, "o": 12.3, "h": 12.35, "l": 12.1, "v": 1622396}, {"date": "2026-02-11", "c": 12.2, "o": 12.1, "h": 12.3, "l": 12.0, "v": 1768544}, {"date": "2026-02-23", "c": 12.35, "o": 12.2, "h": 12.45, "l": 12.1, "v": 1529079}, {"date": "2026-02-24", "c": 12.45, "o": 12.35, "h": 12.65, "l": 12.35, "v": 1190546}, {"date": "2026-02-25", "c": 12.3, "o": 12.45, "h": 12.5, "l": 12.15, "v": 1610791}, {"date": "2026-02-26", "c": 12.35, "o": 12.3, "h": 12.4, "l": 12.2, "v": 1022845}, {"date": "2026-03-02", "c": 12.0, "o": 12.0, "h": 12.25, "l": 11.95, "v": 1881403}, {"date": "2026-03-03", "c": 12.25, "o": 12.05, "h": 12.35, "l": 12.0, "v": 1909653}, {"date": "2026-03-04", "c": 11.65, "o": 12.1, "h": 12.2, "l": 11.65, "v": 2467863}, {"date": "2026-03-05", "c": 12.0, "o": 11.95, "h": 12.1, "l": 11.75, "v": 1522305}, {"date": "2026-03-06", "c": 12.2, "o": 12.05, "h": 12.3, "l": 11.95, "v": 1000910}, {"date": "2026-03-09", "c": 11.25, "o": 11.8, "h": 11.8, "l": 11.15, "v": 3153659}, {"date": "2026-03-10", "c": 11.2, "o": 11.45, "h": 11.7, "l": 11.2, "v": 1178677}, {"date": "2026-03-11", "c": 11.75, "o": 11.35, "h": 11.8, "l": 11.35, "v": 1097273}, {"date": "2026-03-12", "c": 11.25, "o": 11.75, "h": 11.75, "l": 11.25, "v": 1473679}, {"date": "2026-03-13", "c": 11.15, "o": 11.2, "h": 11.35, "l": 11.0, "v": 1302578}, {"date": "2026-03-16", "c": 11.2, "o": 11.3, "h": 11.3, "l": 11.1, "v": 1122619}, {"date": "2026-03-17", "c": 11.2, "o": 11.3, "h": 11.4, "l": 11.2, "v": 1394068}, {"date": "2026-03-18", "c": 11.45, "o": 11.35, "h": 11.45, "l": 11.3, "v": 1783934}, {"date": "2026-03-19", "c": 11.25, "o": 11.55, "h": 11.55, "l": 11.25, "v": 1548080}, {"date": "2026-03-20", "c": 11.55, "o": 11.25, "h": 11.6, "l": 11.2, "v": 1816826}, {"date": "2026-03-23", "c": 11.3, "o": 11.4, "h": 11.75, "l": 11.2, "v": 1386017}, {"date": "2026-03-24", "c": 11.35, "o": 11.4, "h": 11.45, "l": 11.25, "v": 989939}, {"date": "2026-03-25", "c": 11.3, "o": 11.7, "h": 11.7, "l": 11.3, "v": 1057313}, {"date": "2026-03-26", "c": 11.2, "o": 11.45, "h": 11.5, "l": 11.2, "v": 923507}, {"date": "2026-03-27", "c": 11.4, "o": 11.4, "h": 11.4, "l": 11.15, "v": 855133}, {"date": "2026-03-30", "c": 11.2, "o": 11.35, "h": 11.35, "l": 11.15, "v": 709774}, {"date": "2026-03-31", "c": 11.1, "o": 11.25, "h": 11.35, "l": 11.0, "v": 1157064}, {"date": "2026-04-01", "c": 11.25, "o": 11.35, "h": 11.5, "l": 11.05, "v": 1598074}, {"date": "2026-04-02", "c": 11.35, "o": 11.4, "h": 11.6, "l": 11.3, "v": 1679713}, {"date": "2026-04-07", "c": 11.2, "o": 11.4, "h": 11.5, "l": 11.15, "v": 850090}, {"date": "2026-04-08", "c": 11.2, "o": 11.2, "h": 11.3, "l": 11.1, "v": 1092386}, {"date": "2026-04-09", "c": 11.05, "o": 11.25, "h": 11.25, "l": 11.05, "v": 996207}, {"date": "2026-04-10", "c": 11.25, "o": 11.2, "h": 11.25, "l": 11.05, "v": 953845}, {"date": "2026-04-13", "c": 10.55, "o": 11.2, "h": 11.2, "l": 10.25, "v": 3895163}, {"date": "2026-04-14", "c": 10.5, "o": 10.5, "h": 10.65, "l": 10.4, "v": 1347921}, {"date": "2026-04-15", "c": 10.75, "o": 10.6, "h": 10.8, "l": 10.5, "v": 1236915}, {"date": "2026-04-16", "c": 10.9, "o": 10.95, "h": 11.05, "l": 10.8, "v": 847542}, {"date": "2026-04-17", "c": 10.55, "o": 11.0, "h": 11.0, "l": 10.5, "v": 1211837}, {"date": "2026-04-20", "c": 10.35, "o": 10.5, "h": 10.5, "l": 10.35, "v": 1294823}, {"date": "2026-04-21", "c": 10.3, "o": 10.35, "h": 10.5, "l": 10.3, "v": 964385}, {"date": "2026-04-22", "c": 10.45, "o": 10.35, "h": 10.45, "l": 10.25, "v": 1043840}, {"date": "2026-04-23", "c": 10.0, "o": 10.35, "h": 10.35, "l": 9.99, "v": 2457845}, {"date": "2026-04-24", "c": 10.1, "o": 10.05, "h": 10.2, "l": 10.0, "v": 1154959}]